tlssysloghandler/__init__.py
tlssysloghandler/handler.py
tlssysloghandler-2.0.0.dist-info/licenses/LICENSE
tlssysloghandler-2.0.0.dist-info/METADATA
tlssysloghandler-2.0.0.dist-info/WHEEL
tlssysloghandler-2.0.0.dist-info/top_level.txt
tlssysloghandler-2.0.0.dist-info/RECORD
