Metadata-Version: 2.4
Name: tlssysloghandler
Version: 2.0.0
Summary: SysLogHandler with TLS
Author-email: A Tammy <atammy@bsd.ac>, Craig Weber <crgwbr@gmail.com>
License: ISC
Project-URL: Repository, https://github.com/bsd-ac/tlssysloghandler
Project-URL: License, https://github.com/bsd-ac/tlssysloghandler/blob/main/LICENSE
Keywords: handler,logging,logger,syslog,tls
Classifier: Programming Language :: Python
Requires-Python: >=3.11
License-File: LICENSE
Dynamic: license-file
